{
    "typeName": "TF::AWS::OpsworksInstance",
    "description": "Provides an OpsWorks instance resource.",
    "sourceUrl": "https://github.com/iann0036/cfn-tf-custom-types.git",
    "documentationUrl": "https://github.com/iann0036/cfn-tf-custom-types/blob/docs/resources/aws/TF-AWS-OpsworksInstance/docs/README.md",
    "definitions": {
        "EbsBlockDeviceDefinition": {
            "type": "object",
            "additionalProperties": false,
            "properties": {
                "DeleteOnTermination": {
                    "type": "boolean"
                },
                "DeviceName": {
                    "type": "string"
                },
                "Iops": {
                    "type": "number"
                },
                "SnapshotId": {
                    "type": "string"
                },
                "VolumeSize": {
                    "type": "number"
                },
                "VolumeType": {
                    "type": "string"
                }
            },
            "required": [
                "DeviceName"
            ]
        },
        "EphemeralBlockDeviceDefinition": {
            "type": "object",
            "additionalProperties": false,
            "properties": {
                "DeviceName": {
                    "type": "string"
                },
                "VirtualName": {
                    "type": "string"
                }
            },
            "required": [
                "DeviceName",
                "VirtualName"
            ]
        },
        "RootBlockDeviceDefinition": {
            "type": "object",
            "additionalProperties": false,
            "properties": {
                "DeleteOnTermination": {
                    "type": "boolean"
                },
                "Iops": {
                    "type": "number"
                },
                "VolumeSize": {
                    "type": "number"
                },
                "VolumeType": {
                    "type": "string"
                }
            },
            "required": []
        },
        "TimeoutsDefinition": {
            "type": "object",
            "additionalProperties": false,
            "properties": {
                "Create": {
                    "type": "string"
                },
                "Delete": {
                    "type": "string"
                },
                "Update": {
                    "type": "string"
                }
            },
            "required": []
        }
    },
    "properties": {
        "tfcfnid": {
            "description": "Internal identifier for tracking resource changes. Do not use.",
            "type": "string"
        },
        "AgentVersion": {
            "type": "string",
            "description": "The AWS OpsWorks agent to install.  Defaults to `\"INHERIT\"`."
        },
        "AmiId": {
            "type": "string",
            "description": "The AMI to use for the instance.  If an AMI is specified, `os` must be `\"Custom\"`."
        },
        "Architecture": {
            "type": "string",
            "description": "Machine architecture for created instances.  Can be either `\"x86_64\"` (the default) or `\"i386\"`."
        },
        "AutoScalingType": {
            "type": "string",
            "description": "Creates load-based or time-based instances.  If set, can be either: `\"load\"` or `\"timer\"`."
        },
        "AvailabilityZone": {
            "type": "string",
            "description": "Name of the availability zone where instances will be created\nby default."
        },
        "CreatedAt": {
            "type": "string"
        },
        "DeleteEbs": {
            "type": "boolean"
        },
        "DeleteEip": {
            "type": "boolean"
        },
        "EbsOptimized": {
            "type": "boolean",
            "description": "If true, the launched EC2 instance will be EBS-optimized."
        },
        "Ec2InstanceId": {
            "type": "string"
        },
        "EcsClusterArn": {
            "type": "string"
        },
        "ElasticIp": {
            "type": "string"
        },
        "Hostname": {
            "type": "string",
            "description": "The instance's host name."
        },
        "Id": {
            "type": "string"
        },
        "InfrastructureClass": {
            "type": "string"
        },
        "InstallUpdatesOnBoot": {
            "type": "boolean",
            "description": "Controls where to install OS and package updates when the instance boots.  Defaults to `true`."
        },
        "InstanceProfileArn": {
            "type": "string"
        },
        "InstanceType": {
            "type": "string",
            "description": "The type of instance to start."
        },
        "LastServiceErrorId": {
            "type": "string"
        },
        "LayerIds": {
            "type": "array",
            "insertionOrder": false,
            "items": {
                "type": "string"
            },
            "description": "The ids of the layers the instance will belong to."
        },
        "Os": {
            "type": "string",
            "description": "Name of operating system that will be installed."
        },
        "Platform": {
            "type": "string"
        },
        "PrivateDns": {
            "type": "string"
        },
        "PrivateIp": {
            "type": "string"
        },
        "PublicDns": {
            "type": "string"
        },
        "PublicIp": {
            "type": "string"
        },
        "RegisteredBy": {
            "type": "string"
        },
        "ReportedAgentVersion": {
            "type": "string"
        },
        "ReportedOsFamily": {
            "type": "string"
        },
        "ReportedOsName": {
            "type": "string"
        },
        "ReportedOsVersion": {
            "type": "string"
        },
        "RootDeviceType": {
            "type": "string",
            "description": "Name of the type of root device instances will have by default.  Can be either `\"ebs\"` or `\"instance-store\"`."
        },
        "RootDeviceVolumeId": {
            "type": "string"
        },
        "SecurityGroupIds": {
            "type": "array",
            "insertionOrder": false,
            "items": {
                "type": "string"
            }
        },
        "SshHostDsaKeyFingerprint": {
            "type": "string"
        },
        "SshHostRsaKeyFingerprint": {
            "type": "string"
        },
        "SshKeyName": {
            "type": "string",
            "description": "Name of the SSH keypair that instances will have by default."
        },
        "StackId": {
            "type": "string",
            "description": "The id of the stack the instance will belong to."
        },
        "State": {
            "type": "string",
            "description": "The desired state of the instance.  Can be either `\"running\"` or `\"stopped\"`."
        },
        "Status": {
            "type": "string"
        },
        "SubnetId": {
            "type": "string",
            "description": "Subnet ID to attach to."
        },
        "Tenancy": {
            "type": "string",
            "description": "Instance tenancy to use. Can be one of `\"default\"`, `\"dedicated\"` or `\"host\"`."
        },
        "VirtualizationType": {
            "type": "string",
            "description": "Keyword to choose what virtualization mode created instances\nwill use. Can be either `\"paravirtual\"` or `\"hvm\"`."
        },
        "EbsBlockDevice": {
            "type": "array",
            "insertionOrder": true,
            "items": {
                "$ref": "#/definitions/EbsBlockDeviceDefinition"
            }
        },
        "EphemeralBlockDevice": {
            "type": "array",
            "insertionOrder": true,
            "items": {
                "$ref": "#/definitions/EphemeralBlockDeviceDefinition"
            }
        },
        "RootBlockDevice": {
            "type": "array",
            "insertionOrder": true,
            "items": {
                "$ref": "#/definitions/RootBlockDeviceDefinition"
            }
        },
        "Timeouts": {
            "$ref": "#/definitions/TimeoutsDefinition"
        }
    },
    "additionalProperties": false,
    "required": [
        "LayerIds",
        "StackId"
    ],
    "readOnlyProperties": [
        "/properties/tfcfnid",
        "/properties/Ec2InstanceId",
        "/properties/Id"
    ],
    "primaryIdentifier": [
        "/properties/tfcfnid"
    ],
    "handlers": {
        "create": {
            "permissions": [
                "s3:GetObject",
                "s3:DeleteObject",
                "lambda:InvokeFunction"
            ]
        },
        "read": {
            "permissions": [
                "s3:GetObject"
            ]
        },
        "update": {
            "permissions": [
                "s3:GetObject",
                "s3:DeleteObject",
                "lambda:InvokeFunction"
            ]
        },
        "delete": {
            "permissions": [
                "s3:GetObject",
                "s3:DeleteObject",
                "lambda:InvokeFunction"
            ]
        },
        "list": {
            "permissions": [
                "s3:GetObject",
                "s3:ListBucket"
            ]
        }
    }
}