{
    "typeName": "Terraform::AWS::EbsSnapshot",
    "description": "CloudFormation equivalent of aws_ebs_snapshot",
    "sourceUrl": "https://github.com/iann0036/cfn-tf-custom-types.git",
    "definitions": {
        "Timeouts": {
            "type": "object",
            "additionalProperties": false,
            "properties": {
                "Create": {
                    "type": "string"
                },
                "Delete": {
                    "type": "string"
                }
            },
            "required": []
        }
    },
    "properties": {
        "tfcfnid": {
            "description": "Internal identifier for tracking resource changes. Do not use.",
            "type": "string"
        },
        "DataEncryptionKeyId": {
            "type": "string"
        },
        "Description": {
            "type": "string"
        },
        "Encrypted": {
            "type": "boolean"
        },
        "Id": {
            "type": "string"
        },
        "KmsKeyId": {
            "type": "string"
        },
        "OwnerAlias": {
            "type": "string"
        },
        "OwnerId": {
            "type": "string"
        },
        "Tags": {
            "type": "array",
            "insertionOrder": true,
            "items": {
                "type": "object",
                "additionalProperties": false,
                "properties": {
                    "Key": {
                        "type": "string"
                    },
                    "Value": {
                        "type": "string"
                    }
                },
                "required": [
                    "Key",
                    "Value"
                ]
            }
        },
        "VolumeId": {
            "type": "string"
        },
        "VolumeSize": {
            "type": "number"
        },
        "Timeouts": {
            "$ref": "#/definitions/Timeouts"
        }
    },
    "additionalProperties": false,
    "required": [
        "VolumeId"
    ],
    "readOnlyProperties": [
        "/properties/tfcfnid",
        "/properties/DataEncryptionKeyId",
        "/properties/Encrypted",
        "/properties/KmsKeyId",
        "/properties/OwnerAlias",
        "/properties/OwnerId",
        "/properties/VolumeSize"
    ],
    "primaryIdentifier": [
        "/properties/tfcfnid"
    ],
    "handlers": {
        "create": {
            "permissions": [
                "*"
            ]
        },
        "read": {
            "permissions": [
                "*"
            ]
        },
        "update": {
            "permissions": [
                "*"
            ]
        },
        "delete": {
            "permissions": [
                "*"
            ]
        },
        "list": {
            "permissions": [
                "*"
            ]
        }
    }
}