{
    "typeName": "Terraform::OVH::PubliccloudUser",
    "description": "~> __DEPRECATED:__ Use [`ovh_cloud_user`](./cloud_user.html) instead.\n\nCreates a user in a public cloud project.",
    "sourceUrl": "https://github.com/iann0036/cfn-tf-custom-types.git",
    "definitions": {},
    "properties": {
        "tfcfnid": {
            "description": "Internal identifier for tracking resource changes. Do not use.",
            "type": "string"
        },
        "CreationDate": {
            "type": "string"
        },
        "Description": {
            "type": "string",
            "description": "A description associated with the user."
        },
        "Id": {
            "type": "string"
        },
        "OpenstackRc": {
            "type": "array",
            "insertionOrder": true,
            "items": {
                "type": "object",
                "additionalProperties": false,
                "properties": {
                    "MapKey": {
                        "type": "string"
                    },
                    "MapValue": {
                        "type": "string"
                    }
                },
                "required": [
                    "MapKey",
                    "MapValue"
                ]
            }
        },
        "Password": {
            "type": "string"
        },
        "ProjectId": {
            "type": "string",
            "description": "The id of the public cloud project. If omitted,\nthe `OVH_PROJECT_ID` environment variable is used."
        },
        "Status": {
            "type": "string"
        },
        "Username": {
            "type": "string"
        }
    },
    "additionalProperties": false,
    "required": [
        "ProjectId"
    ],
    "readOnlyProperties": [
        "/properties/tfcfnid",
        "/properties/CreationDate",
        "/properties/Id",
        "/properties/Password",
        "/properties/Status",
        "/properties/Username"
    ],
    "primaryIdentifier": [
        "/properties/tfcfnid"
    ],
    "handlers": {
        "create": {
            "permissions": [
                "s3:PutObject",
                "secretsmanager:GetSecretValue"
            ]
        },
        "read": {
            "permissions": []
        },
        "update": {
            "permissions": [
                "s3:GetObject",
                "s3:PutObject",
                "secretsmanager:GetSecretValue"
            ]
        },
        "delete": {
            "permissions": [
                "s3:GetObject",
                "s3:DeleteObject",
                "secretsmanager:GetSecretValue"
            ]
        },
        "list": {
            "permissions": []
        }
    }
}