{"CREATE": {"/ClusterInfo": [{"MapKey": "", "MapValue": ""}], "/SddcSize": [{"MapKey": "", "MapValue": ""}], "/AccountLinkSddcConfig": [{"ConnectedAccountId": "", "CustomerSubnetIds": [""]}], "/MicrosoftLicensingConfig": [{"MssqlLicensing": "", "WindowsLicensing": ""}]}, "UPDATE": {"/ClusterInfo": [{"MapKey": "", "MapValue": ""}], "/SddcSize": [{"MapKey": "", "MapValue": ""}], "/AccountLinkSddcConfig": [{"ConnectedAccountId": "", "CustomerSubnetIds": [""]}], "/MicrosoftLicensingConfig": [{"MssqlLicensing": "", "WindowsLicensing": ""}]}}