{
    "typeName": "TF::FortiOS::SystemGeoipoverride",
    "description": "Configure geographical location mapping for IP address(es) to override mappings from FortiGuard.",
    "sourceUrl": "https://github.com/iann0036/cfn-tf-custom-types.git",
    "documentationUrl": "https://github.com/iann0036/cfn-tf-custom-types/blob/docs/resources/fortios/TF-FortiOS-SystemGeoipoverride/docs/README.md",
    "definitions": {
        "Ip6RangeDefinition": {
            "type": "object",
            "additionalProperties": false,
            "properties": {
                "EndIp": {
                    "type": "string",
                    "description": "Ending IP address, inclusive, of the address range (format: xxxx:xxxx:xxxx:xxxx:xxxx:xxxx:xxxx:xxxx)."
                },
                "Id": {
                    "type": "number",
                    "description": "ID of individual entry in the IPv6 range table."
                },
                "StartIp": {
                    "type": "string",
                    "description": "Starting IP address, inclusive, of the address range (format: xxxx:xxxx:xxxx:xxxx:xxxx:xxxx:xxxx:xxxx)."
                }
            },
            "required": []
        },
        "IpRangeDefinition": {
            "type": "object",
            "additionalProperties": false,
            "properties": {
                "EndIp": {
                    "type": "string",
                    "description": "Final IP address, inclusive, of the address range (format: xxx.xxx.xxx.xxx)."
                },
                "Id": {
                    "type": "number",
                    "description": "ID number for individual entry in the IP-Range table."
                },
                "StartIp": {
                    "type": "string",
                    "description": "Starting IP address, inclusive, of the address range (format: xxx.xxx.xxx.xxx)."
                }
            },
            "required": []
        }
    },
    "properties": {
        "tfcfnid": {
            "description": "Internal identifier for tracking resource changes. Do not use.",
            "type": "string"
        },
        "CountryId": {
            "type": "string",
            "description": "Two character Country ID code."
        },
        "Description": {
            "type": "string",
            "description": "Description."
        },
        "DynamicSortSubtable": {
            "type": "string",
            "description": "true or false, set this parameter to true when using dynamic for_each + toset to configure and sort sub-tables, please do not set this parameter when configuring static sub-tables."
        },
        "Id": {
            "type": "string"
        },
        "Name": {
            "type": "string",
            "description": "Location name."
        },
        "Vdomparam": {
            "type": "string",
            "description": "Specifies the vdom to which the resource will be applied when the FortiGate unit is running in VDOM mode. Only one vdom can be specified. If you want to inherit the vdom configuration of the provider, please do not set this parameter."
        },
        "Ip6Range": {
            "type": "array",
            "insertionOrder": false,
            "items": {
                "$ref": "#/definitions/Ip6RangeDefinition"
            }
        },
        "IpRange": {
            "type": "array",
            "insertionOrder": false,
            "items": {
                "$ref": "#/definitions/IpRangeDefinition"
            }
        }
    },
    "additionalProperties": false,
    "required": [
        "Name"
    ],
    "readOnlyProperties": [
        "/properties/tfcfnid",
        "/properties/Id"
    ],
    "primaryIdentifier": [
        "/properties/tfcfnid"
    ],
    "handlers": {
        "create": {
            "permissions": [
                "s3:GetObject",
                "s3:DeleteObject",
                "lambda:InvokeFunction"
            ]
        },
        "read": {
            "permissions": [
                "s3:GetObject"
            ]
        },
        "update": {
            "permissions": [
                "s3:GetObject",
                "s3:DeleteObject",
                "lambda:InvokeFunction"
            ]
        },
        "delete": {
            "permissions": [
                "s3:GetObject",
                "s3:DeleteObject",
                "lambda:InvokeFunction"
            ]
        },
        "list": {
            "permissions": [
                "s3:GetObject",
                "s3:ListBucket"
            ]
        }
    }
}